keeprofi/__init__.py
keeprofi/connection.py
keeprofi/connection_secure.py
keeprofi/logger.py
keeprofi/request.py
keeprofi/response.py
keeprofi/client/__init__.py
keeprofi/config/__init__.py
keeprofi/config/cache.py
keeprofi/config/resource.py
keeprofi/config/settings.py
keeprofi/lib/__init__.py
keeprofi/lib/keyring.py
keeprofi/lib/notify.py
keeprofi/lib/singleton.py
keeprofi/navigator/__init__.py
keeprofi/navigator/fsNavigator.py
keeprofi/navigator/kpEntryNavigator.py
keeprofi/navigator/kpNavigator.py
keeprofi/navigator/navigator.py
keeprofi/server/__init__.py
keeprofi/server/client_process.py
keeprofi/server/keybinds.py
keeprofi/server/keyring.py
keeprofi/server/notify.py
keeprofi/server/server.py
keeprofi/server/resource/__init__.py
keeprofi/server/resource/cache.py
keeprofi/server/resource/config.py
keeprofi/server/resource/resource.py
keeprofi/server/state/__init__.py
keeprofi/server/state/fs_navigation.py
keeprofi/server/state/init.py
keeprofi/server/state/kp_entry_navigation.py
keeprofi/server/state/kp_navigation.py
keeprofi/server/state/kp_open.py
keeprofi/server/state/kp_open_keyring.py
keeprofi/server/state/kp_open_user.py
keeprofi/server/state/navigation.py
keeprofi/server/state/state.py
keeprofi-2.0.2.dist-info/LICENSE
keeprofi-2.0.2.dist-info/METADATA
keeprofi-2.0.2.dist-info/WHEEL
keeprofi-2.0.2.dist-info/entry_points.txt
keeprofi-2.0.2.dist-info/top_level.txt
keeprofi-2.0.2.dist-info/RECORD
