Metadata-Version: 2.1
Name: keeprofi
Version: 2.0.2
Summary: Fast rofi drun menu for keepass database
Home-page: https://gitlab.com/hxss-linux/keeprofi
Author: hxss
Author-email: hxss@ya.ru
Keywords: keepass,rofi,keyring
Classifier: Programming Language :: Python :: 3.7
Classifier: License :: OSI Approved :: MIT License
Classifier: Operating System :: POSIX :: Linux
Classifier: Topic :: Utilities
Requires-Python: >=3.7
License-File: LICENSE
Requires-Dist: pyxdg >=0.26
Requires-Dist: pyyaml >=5.1
Requires-Dist: xerox >=0.4.1
Requires-Dist: pynput >=1.4.2
Requires-Dist: pykeepass >=3.0.3
Requires-Dist: keyring >=19.0.1
Requires-Dist: desktop-notify >=1.2.1
Requires-Dist: hxss.responsibility >=0.1.1
